llm_conversation/__init__.py
llm_conversation/ai_agent.py
llm_conversation/config.py
llm_conversation/conversation_manager.py
llm_conversation-0.1.0.dist-info/LICENSE
llm_conversation-0.1.0.dist-info/METADATA
llm_conversation-0.1.0.dist-info/WHEEL
llm_conversation-0.1.0.dist-info/entry_points.txt
llm_conversation-0.1.0.dist-info/RECORD
