Metadata-Version: 2.3
Name: llm-conversation
Version: 0.1.0
Summary: A tool for LLM agent conversations
License: AGPL-3.0-or-later
Keywords: llm,conversation,ai,agent,chat,prompt
Author: Famiu Haque
Author-email: famiuhaque@proton.me
Requires-Python: >=3.13,<4.0
Classifier: Development Status :: 2 - Pre-Alpha
Classifier: Intended Audience :: Developers
Classifier: Intended Audience :: Education
Classifier: Intended Audience :: Science/Research
Classifier: Environment :: Console
Classifier: License :: OSI Approved :: GNU Affero General Public License v3 or later (AGPLv3+)
Classifier: Programming Language :: Python :: 3.13
Classifier: Programming Language :: Python :: 3 :: Only
Classifier: Topic :: Scientific/Engineering :: Artificial Intelligence
Classifier: Typing :: Typed
Requires-Dist: ollama (>=0.4.7,<0.5.0)
Requires-Dist: prompt_toolkit (>=3.0.50,<4.0.0)
Requires-Dist: pydantic (>=2.10.6,<3.0.0)
Requires-Dist: rich (>=13.9.4,<14.0.0)
Project-URL: Documentation, https://github.com/famiu/llm_conversation/blob/main/README.md
Project-URL: Homepage, https://github.com/famiu/llm_conversation
Project-URL: issues, https://github.com/famiu/llm_conversation/issues
Project-URL: source, https://github.com/famiu/llm_conversation
